[
    {
      "url": "/assets/images/flood.png",
      "title": "Character Sketch"
    },
    {
      "url": "/assets/artwork/painting1.jpg",
      "title": "Digital Painting"
    },
    {
      "url": "/assets/artwork/environment1.jpg",
      "title": "Environment Concept"
    },
    {
      "url": "/assets/artwork/portrait1.jpg",
      "title": "Portrait Study"
    },
    {
      "url": "/assets/artwork/portrait1.jpg",
      "title": "Portrait Study"
    },
    {
      "url": "/assets/artwork/portrait1.jpg",
      "title": "Portrait Study"
    },
    {
      "url": "/assets/artwork/portrait1.jpg",
      "title": "Portrait Study"
    }
  ]
  